pop_finder/.gitignore
pop_finder/.readthedocs.yml
pop_finder/__init__.py
pop_finder/cli_classifier.py
pop_finder/cli_regressor.py
pop_finder/contour_classifier.py
pop_finder/locator_mod.py
pop_finder/pop_finder.py
pop_finder-1.0.10.dist-info/entry_points.txt
pop_finder-1.0.10.dist-info/LICENSE
pop_finder-1.0.10.dist-info/WHEEL
pop_finder-1.0.10.dist-info/METADATA
pop_finder-1.0.10.dist-info/RECORD
