Metadata-Version: 2.1
Name: pop-finder
Version: 1.0.10
Summary: "Python package that uses neural networks for population assignment"
License: MIT
Author: Katie Birchard
Author-email: birchardkatie@gmail.com
Requires-Python: >=3.7.1,<3.10
Classifier: License :: OSI Approved :: MIT License
Classifier: Programming Language :: Python :: 3
Classifier: Programming Language :: Python :: 3.8
Classifier: Programming Language :: Python :: 3.9
Provides-Extra: tf
Requires-Dist: h5py (==2.10.0)
Requires-Dist: keras-tuner (==1.0.2)
Requires-Dist: matplotlib (==3.3.2)
Requires-Dist: numpy (==1.19.5)
Requires-Dist: pandas (==1.1.5)
Requires-Dist: scikit-allel (==1.3.0)
Requires-Dist: scikit-learn (==0.23)
Requires-Dist: scipy (>=1.6.0,<2.0.0)
Requires-Dist: seaborn (>=0.11.1,<0.12.0)
Requires-Dist: tensorflow (==2.4.1); extra == "tf"
Requires-Dist: tensorflow-cpu (==2.4.1)
Requires-Dist: tqdm (>=4.59.0,<5.0.0)
Requires-Dist: wheel (>=0.35.1,<0.36.0)
Requires-Dist: zarr (>=2.6.1,<3.0.0)
